spatialentropy/__init__.py
spatialentropy/_altieri_entropy.py
spatialentropy/_leibovici_entropy.py
spatialentropy/_utils.py
spatialentropy-0.1.0.dist-info/LICENSE
spatialentropy-0.1.0.dist-info/METADATA
spatialentropy-0.1.0.dist-info/WHEEL
spatialentropy-0.1.0.dist-info/top_level.txt
spatialentropy-0.1.0.dist-info/RECORD
