Metadata-Version: 2.1
Name: spatialentropy
Version: 0.1.0
Summary: A python implementation of spatial entropy
Home-page: https://github.com/Mr-Milk/SpatialEntropy
Author: Mr-Milk
Author-email: zym.zym1220@gmail.com
License: UNKNOWN
Platform: UNKNOWN
Classifier: Programming Language :: Python :: 3
Classifier: License :: OSI Approved :: MIT License
Classifier: Operating System :: OS Independent
Requires-Python: >=3.5
Requires-Dist: numpy
Requires-Dist: scikit-learn
Requires-Dist: neighborhood-analysis
